feedback_ui/__init__.py
feedback_ui/cli.py
feedback_ui/main_window.py
feedback_ui/resources_rc.py
feedback_ui/dialogs/__init__.py
feedback_ui/dialogs/draggable_list_widget.py
feedback_ui/dialogs/manage_canned_responses_dialog.py
feedback_ui/dialogs/select_canned_response_dialog.py
feedback_ui/dialogs/settings_dialog.py
feedback_ui/images/1.png
feedback_ui/images/feedback.png
feedback_ui/resources/resources.qrc
feedback_ui/resources/sounds/notification.wav
feedback_ui/resources/translations/en_US.qm
feedback_ui/resources/translations/en_US.ts
feedback_ui/styles/dark_theme.qss
feedback_ui/styles/light_theme.qss
feedback_ui/utils/__init__.py
feedback_ui/utils/ansi_parser.py
feedback_ui/utils/audio_manager.py
feedback_ui/utils/constants.py
feedback_ui/utils/image_processor.py
feedback_ui/utils/object_pool.py
feedback_ui/utils/platform_utils.py
feedback_ui/utils/powershell_formatter.py
feedback_ui/utils/resource_manager.py
feedback_ui/utils/settings_manager.py
feedback_ui/utils/style_manager.py
feedback_ui/utils/text_formatter.py
feedback_ui/utils/theme_colors.py
feedback_ui/utils/ui_factory.py
feedback_ui/utils/ui_helpers.py
feedback_ui/widgets/__init__.py
feedback_ui/widgets/clickable_label.py
feedback_ui/widgets/feedback_text_edit.py
feedback_ui/widgets/image_preview.py
feedback_ui/widgets/loading_overlay.py
feedback_ui/widgets/screenshot_window.py
feedback_ui/widgets/selectable_label.py
interactive_feedback-2.5.10.3.dist-info/licenses/LICENSE
interactive_feedback_server/__init__.py
interactive_feedback_server/cli.py
interactive_feedback_server/core/__init__.py
interactive_feedback_server/core/singleton_manager.py
interactive_feedback_server/core/stats_collector.py
interactive_feedback_server/error_handling/__init__.py
interactive_feedback_server/error_handling/error_handler.py
interactive_feedback_server/error_handling/error_types.py
interactive_feedback_server/error_handling/recovery_manager.py
interactive_feedback_server/llm/__init__.py
interactive_feedback_server/llm/base.py
interactive_feedback-2.5.10.3.dist-info/METADATA
interactive_feedback-2.5.10.3.dist-info/WHEEL
interactive_feedback-2.5.10.3.dist-info/entry_points.txt
interactive_feedback-2.5.10.3.dist-info/top_level.txt
interactive_feedback-2.5.10.3.dist-info/RECORD
