Metadata-Version: 2.4
Name: interactive-feedback
Version: 2.5.10.3
Summary: Enhanced MCP server for interactive user feedback with rich file drag-drop, smart canned responses preview, and optimized UI experience in AI-assisted development.
Author: Fábio Ferreira, Pau Oliva
Author-email: pawa <pawaovo@example.com>
License-Expression: MIT
Project-URL: Homepage, https://github.com/pawaovo/interactive-feedback-mcp
Project-URL: Repository, https://github.com/pawaovo/interactive-feedback-mcp
Project-URL: Issues, https://github.com/pawaovo/interactive-feedback-mcp/issues
Project-URL: Documentation, https://github.com/pawaovo/interactive-feedback-mcp#readme
Keywords: mcp,ai,feedback,interactive,cursor,claude
Classifier: Development Status :: 4 - Beta
Classifier: Intended Audience :: Developers
Classifier: Operating System :: OS Independent
Classifier: Programming Language :: Python :: 3
Classifier: Programming Language :: Python :: 3.11
Classifier: Programming Language :: Python :: 3.12
Classifier: Topic :: Software Development
Classifier: Topic :: Communications
Classifier: Topic :: Scientific/Engineering :: Artificial Intelligence
Requires-Python: >=3.11
License-File: LICENSE
Requires-Dist: fastmcp>=2.0.0
Requires-Dist: psutil>=7.0.0
Requires-Dist: PySide6-Essentials>=6.8.2.1
Requires-Dist: pyperclip>=1.8.2
Requires-Dist: Pillow>=9.0.0
Requires-Dist: pywin32>=228; sys_platform == "win32"
Requires-Dist: openai>=1.0.0
Provides-Extra: audio
Provides-Extra: dev
Requires-Dist: black; extra == "dev"
Requires-Dist: pre-commit; extra == "dev"
Requires-Dist: build; extra == "dev"
Requires-Dist: twine; extra == "dev"
Dynamic: license-file
